Metadata-Version: 1.1
Name: vkdelivery
Version: 0.5
Summary: Module for sending to users of Vkontakte communities.
Home-page: https://github.com/DaniilChizhevskii/vkdelivery
Author: Daniil Chizhevskij
Author-email: daniilchizhevskij@gmail.com
License: UNKNOWN
Platform: UNKNOWN
Classifier: Programming Language :: Python :: 3
Classifier: License :: OSI Approved :: GNU General Public License v3 (GPLv3)
Classifier: Operating System :: OS Independent
